{
  "RLQC29LL": 5326,
  "P88GUJ99": 5301,
  "8000QP00C": 5301,
  "2YV9PCJ2": 5292,
  "UJYPGQ00": 5272,
  "CJQVV20U": 5260,
  "VR8R0LR": 5258,
  "2020PVGQ2": 5255,
  "20YJ90RG": 5247,
  "99P8J0PQ": 5241,
  "LRL0J2R0C": 5240,
  "QQJ822VUJ": 5235,
  "9VJUU8QPQ": 5234,
  "9QP2YQQ8": 5232,
  "8JYUCPGG": 5228,
  "QP8QL9098": 5227,
  "L80GRVVQG": 5224,
  "8YCP9VLLG": 5216,
  "20YCRR2C0": 5208,
  "89892YLQP": 5206,
  "PVCJLJUGV": 5206,
  "2RLPJC92": 5204,
  "YQ2Y0P8GR": 5204,
  "98Y2J2UV": 5203,
  "UR0Y0VRV": 5200,
  "YR8YRY8": 5197,
  "888P8JQG": 5194,
  "QGVCLUG8P": 5192,
  "YY0LGG9P": 5192,
  "9R0GJ9YY": 5191,
  "YVCUGRRJ9": 5189,
  "QYJR9G2GV": 5184,
  "2LLRQCYVL": 5183,
  "GQQ8C2RY": 5179,
  "JPJLGYYL": 5178,
  "98JURQUQ": 5178,
  "YJQ98YCQ": 5177,
  "8GC9L2UCJ": 5176,
  "9UYQYG9C8": 5175,
  "LGQLVV8J9": 5172,
  "2GY2LG9JP": 5169,
  "YYR98GJ9Y": 5167,
  "9PC09GUGY": 5166,
  "80CRGVY0Y": 5166,
  "GP99Q0JV8": 5164,
  "Y29L2CRUR": 5163,
  "29GCP0CL0": 5160,
  "2YU88PCRQ": 5159,
  "YU2C0JP0R": 5153,
  "2QPQC29Y": 5153,
  "29PQCR0L": 5148,
  "2UGYU9RR": 5148,
  "Y8UGV8JP0": 5147,
  "CPYPYVQ9": 5146,
  "G9VGRV02": 5146,
  "88GR9CLGC": 5146,
  "2L2LR99UL": 5140,
  "Y0UQ280QY": 5138,
  "P2C8LPY9J": 5137,
  "9UYVV0Y09": 5137,
  "LV8LYYP0": 5136,
  "YCQUYP8VR": 5135,
  "2QLRRPGU2": 5135,
  "9YRURRQP": 5134,
  "9PCJ0U8U": 5133,
  "QG2Y088Y": 5133,
  "Y0P2QRPYR": 5133,
  "8QGQJLP": 5130,
  "9J00QCUJ": 5130,
  "L00Q2QLYJ": 5128,
  "RRYRLQCV": 5127,
  "L08P2YVRR": 5125,
  "2UQ8JP8GJ": 5125,
  "GQJC9YCQV": 5122,
  "QYCJQJCU": 5121,
  "PVC202C0R": 5120,
  "U2LRL20J": 5120,
  "PQLL20CL9": 5120,
  "22LCYJ00J": 5120,
  "P0RV89CY": 5115,
  "LVV0800P": 5113,
  "Q9P8C0LY": 5110,
  "2GLV0QYJJ": 5110,
  "9CJ2C0YR": 5109,
  "QU9RYGY": 5107,
  "28RGLU8LQ": 5106,
  "UPY0UU2C": 5106,
  "2LJ0P2GVU": 5105,
  "8L8UYPGUR": 5104,
  "JJC0GLV8": 5103,
  "UGG0QV2L": 5103,
  "89V2UY8VG": 5101,
  "V2YQVJJ": 5099,
  "Q2LLC0V9Q": 5098,
  "L99CR9RJR": 5097,
  "2PVPP0RY9": 5093,
  "P0U8GY0P": 5093,
  "8P0Y980PP": 5092,
  "8U0002PV": 5092,
  "PU9L8VVV8": 5092
}